asrpy/__init__.py
asrpy/asr.py
asrpy/asr_utils.py
asrpy-0.0.8.dist-info/LICENSE
asrpy-0.0.8.dist-info/METADATA
asrpy-0.0.8.dist-info/WHEEL
asrpy-0.0.8.dist-info/top_level.txt
asrpy-0.0.8.dist-info/RECORD
