Metadata-Version: 2.1
Name: asrpy
Version: 0.0.8
Summary: Artifact Subspace Reconstruction in Python.
Home-page: https://github.com/DiGyt/asrpy
Author: Dirk Gütlin
Author-email: dirk.guetlin@gmail.com
License: BSD-3
Keywords: EEG MEG Signal Processing
Classifier: Development Status :: 3 - Alpha
Classifier: Topic :: Utilities
Classifier: License :: OSI Approved :: BSD License
License-File: LICENSE
Requires-Dist: numpy
Requires-Dist: scipy
Requires-Dist: mne
Provides-Extra: dev
Requires-Dist: pytest; extra == "dev"
Requires-Dist: flake8; extra == "dev"
Requires-Dist: pytest-cov; extra == "dev"
Requires-Dist: pdoc3; extra == "dev"
